setup.py
django_encrypted_cookie_session.egg-info/PKG-INFO
django_encrypted_cookie_session.egg-info/SOURCES.txt
django_encrypted_cookie_session.egg-info/dependency_links.txt
django_encrypted_cookie_session.egg-info/entry_points.txt
django_encrypted_cookie_session.egg-info/requires.txt
django_encrypted_cookie_session.egg-info/top_level.txt
encrypted_cookies/__init__.py
encrypted_cookies/crypto.py
encrypted_cookies/keygen.py
encrypted_cookies/models.py
encrypted_cookies/tests.py