Metadata-Version: 1.0
Name: django-encrypted-cookie-session
Version: 3.0.0
Summary: Encrypted cookie session backend.
Home-page: http://github.com/brightinteractive/django-encrypted-cookie-session/
Author: Bright Interactive
Author-email: francis@bright-interactive.co.uk
License: BSD
Platform: UNKNOWN
